MANIFEST.in
setup.py
mdemos/__init__.py
mdemos.chat.egg-info/PKG-INFO
mdemos.chat.egg-info/SOURCES.txt
mdemos.chat.egg-info/dependency_links.txt
mdemos.chat.egg-info/entry_points.txt
mdemos.chat.egg-info/namespace_packages.txt
mdemos.chat.egg-info/not-zip-safe
mdemos.chat.egg-info/requires.txt
mdemos.chat.egg-info/top_level.txt
mdemos/chat/__init__.py
mdemos/chat/chat.py
mdemos/chat/static/chat.css
mdemos/chat/static/chrome.js
mdemos/chat/static/gui.js
mdemos/chat/static/index.html
mdemos/chat/static/irc2.js
mdemos/chat/static/style.css
mdemos/chat/static/willowchat.js
mdemos/chat/static/themes/dojo/chrome.js
mdemos/chat/static/themes/dojo/gui.js
mdemos/chat/static/themes/dojo/index.html
mdemos/chat/static/themes/dojo/style.css
mdemos/chat/static/themes/simple/chrome.js
mdemos/chat/static/themes/simple/gui.js
mdemos/chat/static/themes/simple/index.html
mdemos/chat/static/themes/simple/style.css
mdemos/chat/templates/__init__.py
mdemos/chat/templates/__init__.pyc
mdemos/chat/templates/bootstrap.mak
mdemos/chat/templates/chat.mak
mdemos/chat/templates/simple.mak