Metadata-Version: 1.0
Name: mdemos.chat
Version: 0.1.2
Summary: Moksha Chat App
Home-page: http://moksha.fedorahosted.org
Author: Luke Macken
Author-email: lmacken@redhat.com
License: ASL 2.0
Platform: UNKNOWN
